MANIFEST.in
README.md
requirements.txt
setup.py
triv/__init__.py
triv/io/__init__.py
triv/io/client/__init__.py
triv/io/client/api.py
trivio.egg-info/PKG-INFO
trivio.egg-info/SOURCES.txt
trivio.egg-info/dependency_links.txt
trivio.egg-info/entry_points.txt
trivio.egg-info/requires.txt
trivio.egg-info/top_level.txt