Metadata-Version: 1.0
Name: trivio
Version: 0.2.2
Summary: triv.io command line client
Home-page: http://github.com/trivio/trivio.client
Author: Scott Robertson
Author-email: scott@triv.io
License: UNKNOWN
Platform: UNKNOWN
Classifier: Programming Language :: Python
Classifier: License :: OSI Approved :: MIT License
Classifier: Operating System :: OS Independent
Classifier: Development Status :: 3 - Alpha
Classifier: Environment :: Web Environment
Classifier: Intended Audience :: Developers
Classifier: Topic :: Software Development
